{"error":"Parsing failed","timestamp":"2026-04-21T01:18:19.6986352Z","source":"enbridge","pipeline":"WE","noticeId":"173691","rawBlobPath":"raw/enbridge/2026-04-18/WE/173691.html","errorDetails":"[{\"name\":\"Get_HTML_Blob_Content\",\"inputs\":{\"uri\":\"https://stdtenoticeappeus2mx01.blob.core.windows.net/critical-notices/raw/enbridge/2026-04-18/WE/173691.html\",\"method\":\"GET\",\"headers\":{\"x-ms-version\":\"2020-10-02\"},\"authentication\":{\"audience\":\"https://storage.azure.com/\",\"type\":\"ManagedServiceIdentity\"}},\"outputs\":{\"statusCode\":200,\"headers\":{\"Accept-Ranges\":\"bytes\",\"ETag\":\"\\\"0x8DE9D60E5EB5B41\\\"\",\"Server\":\"Windows-Azure-Blob/1.0,Microsoft-HTTPAPI/2.0\",\"x-ms-request-id\":\"89536a68-d01e-0006-3e2c-d1a15f000000\",\"x-ms-client-request-id\":\"a4fff9a2-376b-4aef-86b8-3aa6cdc16545\",\"x-ms-version\":\"2020-10-02\",\"x-ms-tag-count\":\"2\",\"x-ms-creation-time\":\"Sat, 18 Apr 2026 15:41:03 GMT\",\"x-ms-lease-status\":\"unlocked\",\"x-ms-lease-state\":\"available\",\"x-ms-blob-type\":\"BlockBlob\",\"x-ms-server-encrypted\":\"true\",\"x-ms-access-tier\":\"Hot\",\"x-ms-access-tier-inferred\":\"true\",\"Date\":\"Tue, 21 Apr 2026 01:18:18 GMT\",\"Content-Length\":\"2405\",\"Content-Type\":\"text/html\",\"Content-MD5\":\"dBNyo/kO54epHnCRaXsVeQ==\",\"Last-Modified\":\"Sat, 18 Apr 2026 15:41:03 GMT\"},\"body\":\"<!-- template.asp -->\\r\\n<html><head><title>Westcoast Energy Limited Partnership 201172186 : Critical Notices</title><link rel=stylesheet href='/styles/infopost.css' type='text/css'><link rel=stylesheet href='NoticeDetail.css' type='text/css'></head><body><div id=main><script type='text/javascript'> function Print() {if (document.queryCommandSupported('print')) {document.execCommand('print', false, null);\\t}else {window.parent.print(); }}</script><div class=recordsetBar><a class=recordsetBar href='javascript:history.go(-1)'>Back</a><a class=recordsetBar href='#' onClick='Print();return false'>Print</a></div><div id=bulletinContents><div class=headingArea><div id=heading>TSP:&nbsp<br>TSP Name:&nbsp<br>Critical Notice Description:&nbsp<br>Notice Effective Date:&nbsp<br>Notice Effective Time:&nbsp<br>Notice End Date:&nbsp<br>Notice End Time:&nbsp<br>Notice Identifier:&nbsp<br>Notice Status Description:&nbsp<br>Notice Type:&nbsp<br>Posting Date:&nbsp<br>Posting Time:&nbsp<br>Prior Notice Identifier:&nbsp<br>Required Response<br>&nbsp; Indicator Description:&nbsp<br>Response Date:&nbsp<br>Response Time:&nbsp<br>Subject:&nbsp<br></div><div id=headingData>243346247<br>Westcoast Energy Limited Partnership<br>Critical notice<br>02/07/2026<br>08:45:32 AM<br>05/08/2026<br>08:19:32 AM<br>173691<br>Initiate<br>Pipeline Conditions<br>02/07/2026<br>08:45:32 AM<br> <br><br>No response required<br> <br> <br>Pipeline Operational Status for Feb 7, 2026 08:30 CCT<br></div></div><br><div id=bulletin><br><div id=heading>Notice Text:</div><br>Linepack Status - Critical<br><br>System Linepack -3318 MMCF<br><br>Target Linepack -3200 MMCF<br><br>Forecasted Linepack - 3302 MMCF<br><br>Physical Operations Notes: Linepack is expected to decrease today.<br><br>Commercial Operations Notes: Shippers must trend their accounts into tolerance. <br><br>The Pipeline Operational & Commercial Status can be found in LINK under: Customer Activities > Flowing Gas > Imbalance > Pipeline Operational & Commercial Status.<br></div><br><br></div><script type='text/javascript'> function Print() {if (document.queryCommandSupported('print')) {document.execCommand('print', false, null);\\t}else {window.parent.print(); }}</script><div class=recordsetBar><a class=recordsetBar href='javascript:history.go(-1)'>Back</a><a class=recordsetBar href='#' onClick='Print();return false'>Print</a></div></table></div></body></html>\"},\"startTime\":\"2026-04-21T01:18:18.5902448Z\",\"endTime\":\"2026-04-21T01:18:19.0115641Z\",\"trackingId\":\"9c0321d4-8e11-4103-b145-086c3e287c90\",\"clientTrackingId\":\"08584248726587816242032559555CU00\",\"code\":\"OK\",\"status\":\"Succeeded\"},{\"name\":\"Call_Foundry_Extraction\",\"startTime\":\"2026-04-21T01:18:19.0415149Z\",\"endTime\":\"2026-04-21T01:18:19.3171516Z\",\"trackingId\":\"1b82612f-0962-40bc-992d-04af8c34f60f\",\"clientTrackingId\":\"08584248726587816242032559555CU00\",\"code\":\"BadRequest\",\"status\":\"Failed\",\"error\":{\"code\":\"InvalidTemplate\",\"message\":\"Unable to process template language expressions in action 'Call_Foundry_Extraction' inputs at line '0' and column '0': 'The workflow parameter 'foundryApiKey' is not found.'.\"}},{\"name\":\"Parse_Foundry_Response\",\"startTime\":\"2026-04-21T01:18:19.3178855Z\",\"endTime\":\"2026-04-21T01:18:19.3182648Z\",\"trackingId\":\"8f29506f-3c9a-4b25-92ef-1dd6c0074142\",\"clientTrackingId\":\"08584248726587816242032559555CU00\",\"code\":\"ActionSkipped\",\"status\":\"Skipped\",\"error\":{\"code\":\"ActionConditionFailed\",\"message\":\"The execution of template action 'Parse_Foundry_Response' is skipped: the 'runAfter' condition for action 'Call_Foundry_Extraction' is not satisfied. Expected status values 'Succeeded' and actual value 'Failed'.\"}},{\"name\":\"Extract_JSON_Content\",\"startTime\":\"2026-04-21T01:18:19.3188825Z\",\"endTime\":\"2026-04-21T01:18:19.3192482Z\",\"trackingId\":\"69514b84-877d-46f3-b953-ded59a1af10c\",\"clientTrackingId\":\"08584248726587816242032559555CU00\",\"code\":\"ActionSkipped\",\"status\":\"Skipped\",\"error\":{\"code\":\"ActionConditionFailed\",\"message\":\"The execution of template action 'Extract_JSON_Content' is skipped: the 'runAfter' condition for action 'Parse_Foundry_Response' is not satisfied. Expected status values 'Succeeded' and actual value 'Skipped'.\"}},{\"name\":\"Build_Final_Parsed_Document\",\"startTime\":\"2026-04-21T01:18:19.3198244Z\",\"endTime\":\"2026-04-21T01:18:19.3201728Z\",\"trackingId\":\"ac0ee4d3-28b2-425c-9a19-990970c3d29f\",\"clientTrackingId\":\"08584248726587816242032559555CU00\",\"code\":\"ActionSkipped\",\"status\":\"Skipped\",\"error\":{\"code\":\"ActionConditionFailed\",\"message\":\"The execution of template action 'Build_Final_Parsed_Document' is skipped: the 'runAfter' condition for action 'Extract_JSON_Content' is not satisfied. Expected status values 'Succeeded' and actual value 'Skipped'.\"}},{\"name\":\"Write_Parsed_JSON_Blob\",\"startTime\":\"2026-04-21T01:18:19.3207081Z\",\"endTime\":\"2026-04-21T01:18:19.321049Z\",\"trackingId\":\"c5e31b44-e50d-4b22-a775-25c484201c11\",\"clientTrackingId\":\"08584248726587816242032559555CU00\",\"code\":\"ActionSkipped\",\"status\":\"Skipped\",\"error\":{\"code\":\"ActionConditionFailed\",\"message\":\"The execution of template action 'Write_Parsed_JSON_Blob' is skipped: the 'runAfter' condition for action 'Build_Final_Parsed_Document' is not satisfied. Expected status values 'Succeeded' and actual value 'Skipped'.\"}}]"}