{"error":"Parsing failed","timestamp":"2026-04-20T23:22:09.8788161Z","source":"enbridge","pipeline":"WE","noticeId":"173892","rawBlobPath":"raw/enbridge/2026-04-18/WE/173892.html","errorDetails":"[{\"name\":\"Get_HTML_Blob_Content\",\"inputs\":{\"uri\":\"https://stdtenoticeappeus2mx01.blob.core.windows.net/critical-notices/raw/enbridge/2026-04-18/WE/173892.html\",\"method\":\"GET\",\"headers\":{\"x-ms-version\":\"2020-10-02\"},\"authentication\":{\"audience\":\"https://storage.azure.com/\",\"type\":\"ManagedServiceIdentity\"}},\"outputs\":{\"statusCode\":200,\"headers\":{\"Accept-Ranges\":\"bytes\",\"ETag\":\"\\\"0x8DE9D60E3B50F71\\\"\",\"Server\":\"Windows-Azure-Blob/1.0,Microsoft-HTTPAPI/2.0\",\"x-ms-request-id\":\"1bc07361-501e-0055-4d1c-d1826b000000\",\"x-ms-client-request-id\":\"68374a4b-5a21-4388-88d9-4d3634a5887e\",\"x-ms-version\":\"2020-10-02\",\"x-ms-tag-count\":\"2\",\"x-ms-creation-time\":\"Sat, 18 Apr 2026 15:40:59 GMT\",\"x-ms-lease-status\":\"unlocked\",\"x-ms-lease-state\":\"available\",\"x-ms-blob-type\":\"BlockBlob\",\"x-ms-server-encrypted\":\"true\",\"x-ms-access-tier\":\"Hot\",\"x-ms-access-tier-inferred\":\"true\",\"Date\":\"Mon, 20 Apr 2026 23:22:09 GMT\",\"Content-Length\":\"2358\",\"Content-Type\":\"text/html\",\"Content-MD5\":\"FXdktzkstUD+3TbztBIuOw==\",\"Last-Modified\":\"Sat, 18 Apr 2026 15:40:59 GMT\"},\"body\":\"<!-- template.asp -->\\r\\n<html><head><title>Westcoast Energy Limited Partnership 201172186 : Critical Notices</title><link rel=stylesheet href='/styles/infopost.css' type='text/css'><link rel=stylesheet href='NoticeDetail.css' type='text/css'></head><body><div id=main><script type='text/javascript'> function Print() {if (document.queryCommandSupported('print')) {document.execCommand('print', false, null);\\t}else {window.parent.print(); }}</script><div class=recordsetBar><a class=recordsetBar href='javascript:history.go(-1)'>Back</a><a class=recordsetBar href='#' onClick='Print();return false'>Print</a></div><div id=bulletinContents><div class=headingArea><div id=heading>TSP:&nbsp<br>TSP Name:&nbsp<br>Critical Notice Description:&nbsp<br>Notice Effective Date:&nbsp<br>Notice Effective Time:&nbsp<br>Notice End Date:&nbsp<br>Notice End Time:&nbsp<br>Notice Identifier:&nbsp<br>Notice Status Description:&nbsp<br>Notice Type:&nbsp<br>Posting Date:&nbsp<br>Posting Time:&nbsp<br>Prior Notice Identifier:&nbsp<br>Required Response<br>&nbsp; Indicator Description:&nbsp<br>Response Date:&nbsp<br>Response Time:&nbsp<br>Subject:&nbsp<br></div><div id=headingData>243346247<br>Westcoast Energy Limited Partnership<br>Critical notice<br>02/12/2026<br>07:26:21 AM<br>05/13/2026<br>07:26:21 AM<br>173892<br>Initiate<br>Capacity Constraint<br>02/12/2026<br>07:26:21 AM<br> <br><br>No response required<br> <br> <br>Huntingdon/Station 2 South Capacity for February 13, 2026<br></div></div><br><div id=bulletin><br><div id=heading>Notice Text:</div><br>Further to Notice #169242, Westcoast will be allowing the following flow on T South:<br><br>Huntingdon Delivery Area Capacity<br><br>February 13, 2026: 2,209,572 GJ<br><br>Station 2 South Capacity<br><br>February 13, 2026: 2,344,412 GJ<br><br>Changes in operating conditions may result in the capacity being recalled on any gas cycle.<br><br>If you have any questions, please contact the CSR hotline at (403) 699-1800.</div><br><br></div><script type='text/javascript'> function Print() {if (document.queryCommandSupported('print')) {document.execCommand('print', false, null);\\t}else {window.parent.print(); }}</script><div class=recordsetBar><a class=recordsetBar href='javascript:history.go(-1)'>Back</a><a class=recordsetBar href='#' onClick='Print();return false'>Print</a></div></table></div></body></html>\"},\"startTime\":\"2026-04-20T23:22:09.7745475Z\",\"endTime\":\"2026-04-20T23:22:09.7968982Z\",\"trackingId\":\"a3280e5d-49ce-49fe-b544-4a6c8c196581\",\"clientTrackingId\":\"08584248795692467253675527579CU00\",\"code\":\"OK\",\"status\":\"Succeeded\"},{\"name\":\"Call_Foundry_Extraction\",\"startTime\":\"2026-04-20T23:22:09.809058Z\",\"endTime\":\"2026-04-20T23:22:09.8380075Z\",\"trackingId\":\"f788a3c5-85b8-4782-bc35-b6669de8bf14\",\"clientTrackingId\":\"08584248795692467253675527579CU00\",\"code\":\"BadRequest\",\"status\":\"Failed\",\"error\":{\"code\":\"InvalidTemplate\",\"message\":\"Unable to process template language expressions in action 'Call_Foundry_Extraction' inputs at line '0' and column '0': 'The workflow parameter 'foundryApiKey' is not found.'.\"}},{\"name\":\"Parse_Foundry_Response\",\"startTime\":\"2026-04-20T23:22:09.8388775Z\",\"endTime\":\"2026-04-20T23:22:09.839607Z\",\"trackingId\":\"762fe328-a466-4eb9-9601-0e6774ae1f0e\",\"clientTrackingId\":\"08584248795692467253675527579CU00\",\"code\":\"ActionSkipped\",\"status\":\"Skipped\",\"error\":{\"code\":\"ActionConditionFailed\",\"message\":\"The execution of template action 'Parse_Foundry_Response' is skipped: the 'runAfter' condition for action 'Call_Foundry_Extraction' is not satisfied. Expected status values 'Succeeded' and actual value 'Failed'.\"}},{\"name\":\"Extract_JSON_Content\",\"startTime\":\"2026-04-20T23:22:09.8401144Z\",\"endTime\":\"2026-04-20T23:22:09.8404211Z\",\"trackingId\":\"3a503bf4-9f5e-43b1-98d0-07756c733689\",\"clientTrackingId\":\"08584248795692467253675527579CU00\",\"code\":\"ActionSkipped\",\"status\":\"Skipped\",\"error\":{\"code\":\"ActionConditionFailed\",\"message\":\"The execution of template action 'Extract_JSON_Content' is skipped: the 'runAfter' condition for action 'Parse_Foundry_Response' is not satisfied. Expected status values 'Succeeded' and actual value 'Skipped'.\"}},{\"name\":\"Build_Final_Parsed_Document\",\"startTime\":\"2026-04-20T23:22:09.8411736Z\",\"endTime\":\"2026-04-20T23:22:09.8415067Z\",\"trackingId\":\"b1fa6f02-bd12-4669-a4b1-e9145b8af941\",\"clientTrackingId\":\"08584248795692467253675527579CU00\",\"code\":\"ActionSkipped\",\"status\":\"Skipped\",\"error\":{\"code\":\"ActionConditionFailed\",\"message\":\"The execution of template action 'Build_Final_Parsed_Document' is skipped: the 'runAfter' condition for action 'Extract_JSON_Content' is not satisfied. Expected status values 'Succeeded' and actual value 'Skipped'.\"}},{\"name\":\"Write_Parsed_JSON_Blob\",\"startTime\":\"2026-04-20T23:22:09.8420745Z\",\"endTime\":\"2026-04-20T23:22:09.842403Z\",\"trackingId\":\"30778bbb-4847-47e2-ba85-4bc8e4a7bd9f\",\"clientTrackingId\":\"08584248795692467253675527579CU00\",\"code\":\"ActionSkipped\",\"status\":\"Skipped\",\"error\":{\"code\":\"ActionConditionFailed\",\"message\":\"The execution of template action 'Write_Parsed_JSON_Blob' is skipped: the 'runAfter' condition for action 'Build_Final_Parsed_Document' is not satisfied. Expected status values 'Succeeded' and actual value 'Skipped'.\"}}]"}