{"error":"Parsing failed","timestamp":"2026-04-21T00:59:42.9257715Z","source":"enbridge","pipeline":"MB","noticeId":"175972","rawBlobPath":"raw/enbridge/2026-04-18/MB/175972.html","errorDetails":"[{\"name\":\"Get_HTML_Blob_Content\",\"inputs\":{\"uri\":\"https://stdtenoticeappeus2mx01.blob.core.windows.net/critical-notices/raw/enbridge/2026-04-18/MB/175972.html\",\"method\":\"GET\",\"headers\":{\"x-ms-version\":\"2020-10-02\"},\"authentication\":{\"audience\":\"https://storage.azure.com/\",\"type\":\"ManagedServiceIdentity\"}},\"outputs\":{\"statusCode\":200,\"headers\":{\"Accept-Ranges\":\"bytes\",\"ETag\":\"\\\"0x8DE9D609561FEDA\\\"\",\"Server\":\"Windows-Azure-Blob/1.0,Microsoft-HTTPAPI/2.0\",\"x-ms-request-id\":\"4f217ca1-301e-0031-732a-d173f3000000\",\"x-ms-client-request-id\":\"c18bbdc1-5714-43fe-b42b-29c2f7f3fa14\",\"x-ms-version\":\"2020-10-02\",\"x-ms-tag-count\":\"2\",\"x-ms-creation-time\":\"Sat, 18 Apr 2026 15:38:48 GMT\",\"x-ms-lease-status\":\"unlocked\",\"x-ms-lease-state\":\"available\",\"x-ms-blob-type\":\"BlockBlob\",\"x-ms-server-encrypted\":\"true\",\"x-ms-access-tier\":\"Hot\",\"x-ms-access-tier-inferred\":\"true\",\"Date\":\"Tue, 21 Apr 2026 00:59:42 GMT\",\"Content-Length\":\"2366\",\"Content-Type\":\"text/html\",\"Content-MD5\":\"dkk1h8TjAwesr5AT81KdSQ==\",\"Last-Modified\":\"Sat, 18 Apr 2026 15:38:48 GMT\"},\"body\":\"<!-- template.asp -->\\r\\n<html><head><title>Market Hub Partners, Moss Bluff Facility 031369874 : Critical Notices</title><link rel=stylesheet href='/styles/infopost.css' type='text/css'><link rel=stylesheet href='NoticeDetail.css' type='text/css'></head><body><div id=main><script type='text/javascript'> function Print() {if (document.queryCommandSupported('print')) {document.execCommand('print', false, null);\\t}else {window.parent.print(); }}</script><div class=recordsetBar><a class=recordsetBar href='javascript:history.go(-1)'>Back</a><a class=recordsetBar href='#' onClick='Print();return false'>Print</a></div><div id=bulletinContents><div class=headingArea><div id=heading>TSP:&nbsp<br>TSP Name:&nbsp<br>Critical Notice Description:&nbsp<br>Notice Effective Date:&nbsp<br>Notice Effective Time:&nbsp<br>Notice End Date:&nbsp<br>Notice End Time:&nbsp<br>Notice Identifier:&nbsp<br>Notice Status Description:&nbsp<br>Notice Type:&nbsp<br>Posting Date:&nbsp<br>Posting Time:&nbsp<br>Prior Notice Identifier:&nbsp<br>Required Response<br>&nbsp; Indicator Description:&nbsp<br>Response Date:&nbsp<br>Response Time:&nbsp<br>Subject:&nbsp<br></div><div id=headingData>031369874<br>Moss Bluff Hub, LLC<br>Critical notice<br>04/02/2026<br>09:00:00 AM<br>04/03/2026<br>09:00:00 AM<br>175972<br>Initiate<br>Capacity Constraint<br>04/01/2026<br>02:30:29 PM<br> <br><br>No response required<br> <br> <br>Moss Bluff Storage Conditions for 04/02/2026<br></div></div><br><div id=bulletin><br><div id=heading>Notice Text:</div><br>The following restriction will be in place on the Moss Bluff Storage (Moss Bluff) system for Gas Day April 2, 2026:<br><br>Moss Bluff has scheduled and sealed injections. No increases in injections will be accepted.<br><br>Customers are advised that capacity may become available as the nomination and confirmation process continues throughout the day.<br><br>Please contact your Operations Account Representative if you have any questions.<br><br><br></div><br><br></div><script type='text/javascript'> function Print() {if (document.queryCommandSupported('print')) {document.execCommand('print', false, null);\\t}else {window.parent.print(); }}</script><div class=recordsetBar><a class=recordsetBar href='javascript:history.go(-1)'>Back</a><a class=recordsetBar href='#' onClick='Print();return false'>Print</a></div></table></div></body></html>\"},\"startTime\":\"2026-04-21T00:59:42.8474174Z\",\"endTime\":\"2026-04-21T00:59:42.8569842Z\",\"trackingId\":\"2d1c077e-9e14-49cb-bfa5-bc7c1bc1f79a\",\"clientTrackingId\":\"08584248738600406909621160061CU00\",\"code\":\"OK\",\"status\":\"Succeeded\"},{\"name\":\"Call_Foundry_Extraction\",\"startTime\":\"2026-04-21T00:59:42.8700989Z\",\"endTime\":\"2026-04-21T00:59:42.8951283Z\",\"trackingId\":\"5a08b7b1-97fb-4e20-88c0-18afffa85d9b\",\"clientTrackingId\":\"08584248738600406909621160061CU00\",\"code\":\"BadRequest\",\"status\":\"Failed\",\"error\":{\"code\":\"InvalidTemplate\",\"message\":\"Unable to process template language expressions in action 'Call_Foundry_Extraction' inputs at line '0' and column '0': 'The workflow parameter 'foundryApiKey' is not found.'.\"}},{\"name\":\"Parse_Foundry_Response\",\"startTime\":\"2026-04-21T00:59:42.8957903Z\",\"endTime\":\"2026-04-21T00:59:42.8961258Z\",\"trackingId\":\"e0115c88-facd-4bcd-910e-ff2588ed2b00\",\"clientTrackingId\":\"08584248738600406909621160061CU00\",\"code\":\"ActionSkipped\",\"status\":\"Skipped\",\"error\":{\"code\":\"ActionConditionFailed\",\"message\":\"The execution of template action 'Parse_Foundry_Response' is skipped: the 'runAfter' condition for action 'Call_Foundry_Extraction' is not satisfied. Expected status values 'Succeeded' and actual value 'Failed'.\"}},{\"name\":\"Extract_JSON_Content\",\"startTime\":\"2026-04-21T00:59:42.8966277Z\",\"endTime\":\"2026-04-21T00:59:42.8969443Z\",\"trackingId\":\"b52f01d0-efb4-47f0-bd69-fec6ff0cd36d\",\"clientTrackingId\":\"08584248738600406909621160061CU00\",\"code\":\"ActionSkipped\",\"status\":\"Skipped\",\"error\":{\"code\":\"ActionConditionFailed\",\"message\":\"The execution of template action 'Extract_JSON_Content' is skipped: the 'runAfter' condition for action 'Parse_Foundry_Response' is not satisfied. Expected status values 'Succeeded' and actual value 'Skipped'.\"}},{\"name\":\"Build_Final_Parsed_Document\",\"startTime\":\"2026-04-21T00:59:42.8974576Z\",\"endTime\":\"2026-04-21T00:59:42.8977838Z\",\"trackingId\":\"dec30c1e-f75a-4341-a718-959e76024788\",\"clientTrackingId\":\"08584248738600406909621160061CU00\",\"code\":\"ActionSkipped\",\"status\":\"Skipped\",\"error\":{\"code\":\"ActionConditionFailed\",\"message\":\"The execution of template action 'Build_Final_Parsed_Document' is skipped: the 'runAfter' condition for action 'Extract_JSON_Content' is not satisfied. Expected status values 'Succeeded' and actual value 'Skipped'.\"}},{\"name\":\"Write_Parsed_JSON_Blob\",\"startTime\":\"2026-04-21T00:59:42.8982903Z\",\"endTime\":\"2026-04-21T00:59:42.8986029Z\",\"trackingId\":\"162f8628-8f4b-4631-9595-6e1f7740c9c0\",\"clientTrackingId\":\"08584248738600406909621160061CU00\",\"code\":\"ActionSkipped\",\"status\":\"Skipped\",\"error\":{\"code\":\"ActionConditionFailed\",\"message\":\"The execution of template action 'Write_Parsed_JSON_Blob' is skipped: the 'runAfter' condition for action 'Build_Final_Parsed_Document' is not satisfied. Expected status values 'Succeeded' and actual value 'Skipped'.\"}}]"}