{"error":"Parsing failed","timestamp":"2026-04-20T23:19:17.9361737Z","source":"enbridge","pipeline":"MB","noticeId":"175972","rawBlobPath":"raw/enbridge/2026-04-18/MB/175972.html","errorDetails":"[{\"name\":\"Get_HTML_Blob_Content\",\"inputs\":{\"uri\":\"https://stdtenoticeappeus2mx01.blob.core.windows.net/critical-notices/raw/enbridge/2026-04-18/MB/175972.html\",\"method\":\"GET\",\"headers\":{\"x-ms-version\":\"2020-10-02\"},\"authentication\":{\"audience\":\"https://storage.azure.com/\",\"type\":\"ManagedServiceIdentity\"}},\"outputs\":{\"statusCode\":200,\"headers\":{\"Accept-Ranges\":\"bytes\",\"ETag\":\"\\\"0x8DE9D609561FEDA\\\"\",\"Server\":\"Windows-Azure-Blob/1.0,Microsoft-HTTPAPI/2.0\",\"x-ms-request-id\":\"431ddab2-701e-000f-731c-d1e48c000000\",\"x-ms-client-request-id\":\"5583df25-df36-4092-87d4-9f24317c7515\",\"x-ms-version\":\"2020-10-02\",\"x-ms-tag-count\":\"2\",\"x-ms-creation-time\":\"Sat, 18 Apr 2026 15:38:48 GMT\",\"x-ms-lease-status\":\"unlocked\",\"x-ms-lease-state\":\"available\",\"x-ms-blob-type\":\"BlockBlob\",\"x-ms-server-encrypted\":\"true\",\"x-ms-access-tier\":\"Hot\",\"x-ms-access-tier-inferred\":\"true\",\"Date\":\"Mon, 20 Apr 2026 23:19:16 GMT\",\"Content-Length\":\"2366\",\"Content-Type\":\"text/html\",\"Content-MD5\":\"dkk1h8TjAwesr5AT81KdSQ==\",\"Last-Modified\":\"Sat, 18 Apr 2026 15:38:48 GMT\"},\"body\":\"<!-- template.asp -->\\r\\n<html><head><title>Market Hub Partners, Moss Bluff Facility 031369874 : Critical Notices</title><link rel=stylesheet href='/styles/infopost.css' type='text/css'><link rel=stylesheet href='NoticeDetail.css' type='text/css'></head><body><div id=main><script type='text/javascript'> function Print() {if (document.queryCommandSupported('print')) {document.execCommand('print', false, null);\\t}else {window.parent.print(); }}</script><div class=recordsetBar><a class=recordsetBar href='javascript:history.go(-1)'>Back</a><a class=recordsetBar href='#' onClick='Print();return false'>Print</a></div><div id=bulletinContents><div class=headingArea><div id=heading>TSP:&nbsp<br>TSP Name:&nbsp<br>Critical Notice Description:&nbsp<br>Notice Effective Date:&nbsp<br>Notice Effective Time:&nbsp<br>Notice End Date:&nbsp<br>Notice End Time:&nbsp<br>Notice Identifier:&nbsp<br>Notice Status Description:&nbsp<br>Notice Type:&nbsp<br>Posting Date:&nbsp<br>Posting Time:&nbsp<br>Prior Notice Identifier:&nbsp<br>Required Response<br>&nbsp; Indicator Description:&nbsp<br>Response Date:&nbsp<br>Response Time:&nbsp<br>Subject:&nbsp<br></div><div id=headingData>031369874<br>Moss Bluff Hub, LLC<br>Critical notice<br>04/02/2026<br>09:00:00 AM<br>04/03/2026<br>09:00:00 AM<br>175972<br>Initiate<br>Capacity Constraint<br>04/01/2026<br>02:30:29 PM<br> <br><br>No response required<br> <br> <br>Moss Bluff Storage Conditions for 04/02/2026<br></div></div><br><div id=bulletin><br><div id=heading>Notice Text:</div><br>The following restriction will be in place on the Moss Bluff Storage (Moss Bluff) system for Gas Day April 2, 2026:<br><br>Moss Bluff has scheduled and sealed injections. No increases in injections will be accepted.<br><br>Customers are advised that capacity may become available as the nomination and confirmation process continues throughout the day.<br><br>Please contact your Operations Account Representative if you have any questions.<br><br><br></div><br><br></div><script type='text/javascript'> function Print() {if (document.queryCommandSupported('print')) {document.execCommand('print', false, null);\\t}else {window.parent.print(); }}</script><div class=recordsetBar><a class=recordsetBar href='javascript:history.go(-1)'>Back</a><a class=recordsetBar href='#' onClick='Print();return false'>Print</a></div></table></div></body></html>\"},\"startTime\":\"2026-04-20T23:19:17.4134535Z\",\"endTime\":\"2026-04-20T23:19:17.4837702Z\",\"trackingId\":\"a4beb527-89aa-4ea7-bdcc-e19e6237f9da\",\"clientTrackingId\":\"08584248798710275683610115286CU00\",\"code\":\"OK\",\"status\":\"Succeeded\"},{\"name\":\"Call_Foundry_Extraction\",\"startTime\":\"2026-04-20T23:19:17.4972615Z\",\"endTime\":\"2026-04-20T23:19:17.8678036Z\",\"trackingId\":\"e7144f26-7b9c-4824-ba21-e43c76145f24\",\"clientTrackingId\":\"08584248798710275683610115286CU00\",\"code\":\"BadRequest\",\"status\":\"Failed\",\"error\":{\"code\":\"InvalidTemplate\",\"message\":\"Unable to process template language expressions in action 'Call_Foundry_Extraction' inputs at line '0' and column '0': 'The workflow parameter 'foundryApiKey' is not found.'.\"}},{\"name\":\"Parse_Foundry_Response\",\"startTime\":\"2026-04-20T23:19:17.8685663Z\",\"endTime\":\"2026-04-20T23:19:17.8689388Z\",\"trackingId\":\"a3bd4ea8-38c0-43fc-9df3-deea106cd341\",\"clientTrackingId\":\"08584248798710275683610115286CU00\",\"code\":\"ActionSkipped\",\"status\":\"Skipped\",\"error\":{\"code\":\"ActionConditionFailed\",\"message\":\"The execution of template action 'Parse_Foundry_Response' is skipped: the 'runAfter' condition for action 'Call_Foundry_Extraction' is not satisfied. Expected status values 'Succeeded' and actual value 'Failed'.\"}},{\"name\":\"Extract_JSON_Content\",\"startTime\":\"2026-04-20T23:19:17.8694815Z\",\"endTime\":\"2026-04-20T23:19:17.8698022Z\",\"trackingId\":\"687aa14b-9e81-45c8-b5f5-e13d5826a764\",\"clientTrackingId\":\"08584248798710275683610115286CU00\",\"code\":\"ActionSkipped\",\"status\":\"Skipped\",\"error\":{\"code\":\"ActionConditionFailed\",\"message\":\"The execution of template action 'Extract_JSON_Content' is skipped: the 'runAfter' condition for action 'Parse_Foundry_Response' is not satisfied. Expected status values 'Succeeded' and actual value 'Skipped'.\"}},{\"name\":\"Build_Final_Parsed_Document\",\"startTime\":\"2026-04-20T23:19:17.8703461Z\",\"endTime\":\"2026-04-20T23:19:17.8706822Z\",\"trackingId\":\"5bcf98f1-f87d-4ed3-b564-1554304d4ec3\",\"clientTrackingId\":\"08584248798710275683610115286CU00\",\"code\":\"ActionSkipped\",\"status\":\"Skipped\",\"error\":{\"code\":\"ActionConditionFailed\",\"message\":\"The execution of template action 'Build_Final_Parsed_Document' is skipped: the 'runAfter' condition for action 'Extract_JSON_Content' is not satisfied. Expected status values 'Succeeded' and actual value 'Skipped'.\"}},{\"name\":\"Write_Parsed_JSON_Blob\",\"startTime\":\"2026-04-20T23:19:17.8712213Z\",\"endTime\":\"2026-04-20T23:19:17.871552Z\",\"trackingId\":\"d91d9c19-63b6-43ab-9087-a4bd446f05ef\",\"clientTrackingId\":\"08584248798710275683610115286CU00\",\"code\":\"ActionSkipped\",\"status\":\"Skipped\",\"error\":{\"code\":\"ActionConditionFailed\",\"message\":\"The execution of template action 'Write_Parsed_JSON_Blob' is skipped: the 'runAfter' condition for action 'Build_Final_Parsed_Document' is not satisfied. Expected status values 'Succeeded' and actual value 'Skipped'.\"}}]"}